{
  "main" : {
    "plan": "Планирование",
    "regularly": "Регулярно",
    "statistic": "Статистика",
    "settings": "Настройки"
  },

  "weekday" : {
    "monday": "Понедельник",
    "tuesday": "Вторник",
    "wednesday": "Среда",
    "thursday": "Четверг",
    "friday": "Пятница",
    "saturday": "Суббота",
    "sunday": "Воскресенье"
  },

  "month" : {
    "january": "Январь",
    "february": "Февраль",
    "march": "Март",
    "april": "Апрель",
    "may": "Май",
    "june": "Июнь",
    "july": "Июль",
    "august": "Август",
    "september": "Сентябрь",
    "october": "Октябрь",
    "november": "Ноябрь",
    "december": "Декабрь"
  },

  "action": {
    "ok": "Ок",
    "cancel": "Отмена",
    "delete": "Удалить",
    "delete_all": "Удалить все",
    "complete": "Завершить"
  },

  "day_of_month" : "{day}, {month}",
  "tasks_for_day:" : "Задачи на день:",
  "task" : "Задача",
  "description" : "Описание",
  "time" : "Время",
  "date" : "Дата",
  "checklist" : "Чек-лист",
  "item" : "Элемент",
  "title" : "Название",
  "repeat_on" : "Повторять по",

  "repeat": {
    "daily": "Ежедневно",
    "weekly": "Еженедельно",
    "monthly": "Ежемесячно",
    "annually": "Ежегодно",
    "custom": "Свой"
  },

  "error": {
    "title_cant_be_empty": "Название не может быть пустым"
  },

  "dialog": {
    "do_u_want_to_delete": "Удалить все или только для текущего дня?"
  }
}